<Alloy>
    <Window class="container">
        <Require id="backCorner" src="backCorner" type="view"/>
        <Require id="homeCorner" src="homeCorner" type="view" if="Alloy.Globals.configured"/>
        <Require id="configCorner" src="configCorner" type="view"/>
        <Label id="Label_wizardTitle"/>
        <Label id="Label_wizardStep"/>
        <Label id="Label_configSelect"/>
        <TableView id="ListView_projects" onClick="chooseProject">
            <TableViewSection id="listSection">
                <TableViewRow height=Ti.UI.FILL>
                    <Label bottom="0" class="centered choice" top="0">Retrieving...</Label>
                </TableViewRow>
            </TableViewSection>
        </TableView>
        <View class="button-wrapper" id="nxtBtn" onClick="wizardContinue">
            <ImageView class="btnMainSecondary"/>
            <Label class="btnText skip"/>
        </View>
    </Window>
</Alloy>
